{
    "email": "E-mail",
    "password": "Mật khẩu",
    "login": "Đăng nhập",
    "forgot_password": "Quên mật khẩu",
    "check_connection": "Vui lòng kiểm tra kết nối của bạn",
    "loading": "phát trực tuyến…",
    "file_not_found": "URL không tìm thấy",
    "next_trails": "Những con đường mòn tiếp theo",
    "profile_setting": "Cài đặt cấu hình",
    "first_name": "Tên đầu tiên",
    "last_name": "Họ",
    "invite": "Mời gọi",
    "new_group": "Nhóm mới",
    "settings": "Cài đặt",
    "type_message": "Nhap thong diep",
    "chat": "Trò chuyện",
    "search": "Tìm kiếm",
    "contacts": "Liên lạc",
    "priority": "Sự ưu tiên",
    "chats": "Trò chuyện",
    "company": "Công ty",
    "team": "Đội",
    "all_chat": "Tất cả các cuộc trò chuyện",
    "profile": "Hồ sơ",
    "internal_storage": "Lưu trữ nội bộ",
    "profile_and_account_setting": "Cài đặt hồ sơ và tài khoản",
    "team_name": "Tên nhóm",
    "title": "Tiêu đề",
    "primary_email": "email chính",
    "secondary_email": "Email phụ",
    "logout": "Đăng xuất",
    "re_login": "Đăng nhập lại",
    "yes": "ĐÚNG",
    "no": "KHÔNG",
    "leaving": "Rời đi?",
    "go_to_my_statistic": "Đi tới thống kê của tôi",
    "choose_opponent": "Chọn đối thủ",
    "lost": "Mất đi",
    "draw": "Vẽ tranh",
    "won": "Giành được",
    "start_battle": "Bắt đầu trận chiến",
    "vs": "VS",
    "ready": "Sẵn sàng",
    "the_leadership_challenge": "THỬ THÁCH LÃNH ĐẠO",
    "battle_mode_summary": "Tóm tắt chế độ chiến đấu",
    "summary_detail": "Chi tiết tóm tắt",
    "total": "Toàn bộ",
    "forgot_link_msg": "Chúng tôi sẽ gửi 'Liên kết Đặt lại' đến email của bạn.",
    "something_went_wrong": "Đã xảy ra sự cố",
    "ai": "AI",
    "ai_info": "Đối thủ này chỉ dành cho huấn luyện.\n Kết quả và bảng thành tích của bạn sẽ không bị ảnh hưởng bởi nó.",
    "decline": "Từ chối",
    "accept": "Chấp nhận",
    "continue_str": "Tiếp tục",
    "battle_result": "Kết quả trận chiến",
    "get_ready_to_battle": "SN SÀNG THAM GIA TRẬN ĐẤU",
    "see_details": "Xem chi tiết",
    "progress": "Phát triển",
    "dummy_url": "https:\/\/www.example.com",
    "no_trail_msg": "Xin lỗi đường mòn này không có sẵn.\n Vui lòng liên hệ với người giám sát của bạn.",
    "email_address": "Địa chỉ email",
    "start_new_battle": "Bắt đầu trận chiến mới",
    "show_scores": "Hiển thị điểm số",
    "points": "Điểm",
    "battles": "Trận đánh",
    "correct_answers": "Câu trả lời đúng",
    "trail": "{\"one\":\"Trail\",\"other\":\"Trails\"}",
    "congratulations": "Xin chúc mừng!",
    "what_do_you_think_about_this": "Bạn nghĩ gì về điều này?",
    "needs_rating_from_you": "Cần đánh giá từ bạn",
    "submit": "Gửi đi",
    "check_it_out": "Kiểm tra nó ra!",
    "my_ratings": "Xếp hạng của tôi",
    "see_summary": "Xem Tóm tắt",
    "try_again": "Thử lại",
    "skip": "Nhảy",
    "stay": "Ở lại",
    "members_by_team": "Thành viên của nhóm",
    "reminder": "Nhắc nhở!",
    "me": "Tôi",
    "vault": "Vault",
    "all_media": "Tất cả các kênh truyền thông",
    "my_likes": "Thích của tôi",
    "crowns": "Vương miện",
    "rewards": "Phần thưởng",
    "accept_our_privacy_and_policy": "Tôi đồng ý với <b> <a href=\"https:\/\/www.riaplay.dev\/documents\/General-Terms-RIA-Play.pdf\"> Điều khoản & Điều kiện <\/a> <\/b> và <b> <a href=\"https:\/\/www.riaplay.dev\/documents\/Privacy-Policy-RIA-Play.pdf\"> Chính sách Bảo mật. <\/a> <\/b>",
    "of": "của",
    "thank_you_for_your_participation": "Cảm ơn bạn vì sự tham gia của bạn",
    "asses_sum_info": "Để xem kết quả của bạn, vui lòng nhấp vào nút bên dưới",
    "go_to_my_results": "Đi đến kết quả của tôi",
    "improve_your_score": "Cải thiện điểm số của bạn:",
    "finished": "Đã kết thúc",
    "review": "Ôn tập",
    "my_rewards": "Giải thưởng của tôi",
    "_4_0": "4.0",
    "_5_0": "5.0",
    "_3_0": "3.0",
    "_2_0": "2.0",
    "_1_0": "1,0",
    "no_results_found": "Không có kết quả nào được tìm thấy",
    "message_info": "Thông tin tin nhắn",
    "read_by": "Đọc bởi",
    "unread_by": "Chưa đọc bởi",
    "type_here": "Nhập ở đây",
    "done": "Làm xong",
    "finished_trails": "Những con đường mòn đã hoàn thành",
    "the_current_answer_will_not_be_saved": "Câu trả lời hiện tại sẽ không được lưu.",
    "ok": "đồng ý",
    "reward_description": "Mô tả phần thưởng",
    "prize_description": "Mô tả giải thưởng",
    "service_master": "Bậc thầy dịch vụ",
    "type_comment": "Nhập bình luận",
    "comment": "Bình luận *",
    "info_alert": "Thông báo thông tin",
    "mobile_number": "Số điện thoại",
    "date_of_birth": "Ngày sinh",
    "english": "TIẾNG ANH",
    "you_can_arrange_the_order_by_dragging_the_box": "Bạn có thể sắp xếp thứ tự bằng cách kéo và thả",
    "choose_file": "Chọn tập tin",
    "from_my_gallery": "Từ phòng trưng bày của tôi",
    "open_camera": "Mở máy ảnh",
    "from_storage": "Từ bộ nhớ",
    "record": "Ghi lại",
    "please_select": "Xin hãy lựa chọn",
    "player_label": "Nhãn người chơi",
    "country": "Quốc gia",
    "state": "Tiểu bang",
    "city": "Tp.",
    "store": "Cửa hàng",
    "chat_item": "Trò chuyện",
    "vault_item": "Vault",
    "me_item": "Tôi",
    "save_changes": "Lưu thay đổi",
    "re_type_new_password": "Gõ lại mật khẩu mới",
    "enter_name": "Nhập tên",
    "nationality": "Quốc tịch",
    "enter_last_name": "Nhập họ",
    "please_select_your_nation": "Vui lòng chọn quốc gia cư trú của bạn",
    "gender": "Giới tính",
    "language": "Ngôn ngữ",
    "notification_setup": "Thiết lập thông báo",
    "mr": "Ông.",
    "ms": "Bệnh đa xơ cứng.",
    "mrs": "Bà.",
    "miss": "Cô",
    "mx": "Mx",
    "failed_to_load_camera": "Không tải được máy ảnh trên thiết bị của bạn",
    "first_name_required": "Tên bắt buộc",
    "last_name_required": "Yêu cầu Tên",
    "enter_confirm_password": "Vui lòng nhập 'xác nhận mật khẩu'",
    "no_trail": "Không có đường mòn. Vui lòng tạo một đường mòn trong cổng thông tin khách hàng.",
    "session_expired": "Phiên của bạn đã hết hạn.",
    "begin": "Bắt đầu",
    "no_description": "Không có mô tả",
    "downloading_file": "Dữ liệu đang tải…",
    "please_check_email_address": "Vui lòng kiểm tra địa chỉ email của bạn",
    "leaderboard": "Bảng xếp hạng",
    "select": "Lựa chọn",
    "option": "Lựa chọn",
    "options": "các tùy chọn",
    "no_minerals_available": "Không có khoáng chất",
    "you": "Bạn",
    "other": "Khác",
    "question": "Câu hỏi {0}",
    "failed_to_get_media": "Không tải được phương tiện",
    "path_not_valid": "Đường dẫn này không hợp lệ",
    "select_file": "Chọn tập tin",
    "no_user_msg": "Trình phát này không được thêm vào danh bạ của bạn.",
    "no_app_found": "Không tìm thấy ứng dụng nào có thể mở tệp",
    "report_error": "Báo cáo chưa sẵn sàng, vui lòng thử lại sau",
    "info_title": "Thông tin",
    "myresult_title": "Kết quả của tôi",
    "compare_title": "Đối chiếu",
    "app_permission": "Cần có quyền ứng dụng để bắt đầu khảo sát",
    "cancel": "Huỷ bỏ",
    "from": "Từ",
    "pending_rating": "Xếp hạng đang chờ xử lý",
    "we_still_need_rate": "Chúng tôi vẫn cần đánh giá của bạn",
    "reminder_challenge_title": "Đừng quên chấp nhận hoặc từ chối thử thách này",
    "reminder_finish_title": "Đừng quên hoàn thành thử thách này trong vòng 24 giờ.",
    "reminder_finish_subtitle": "Nếu không bạn sẽ tự động mất",
    "opponent_changed_title": "{0} không phản hồi thách thức của bạn.",
    "opponent_changed_subtitle": "Đối thủ của bạn được đổi thành {0}",
    "accepted_title": "Đã chấp nhận thử thách!",
    "accepted_subtitle": "{0} đã chấp nhận thử thách",
    "finished_title": "Chế độ chiến đấu đã hoàn thành",
    "finished_subtitle": "{0} đã hoàn thành thử thách",
    "decline_title": "Thử thách bị từ chối",
    "decline_subtitle": "{0} đã từ chối thử thách",
    "challenge_title": "Bạn đã được thử thách",
    "challenge_subtitle": "{0} đã gửi cho bạn một thử thách",
    "es_try_info": "Bạn sẽ có thể làm lại bài kiểm tra, nhưng các câu trả lời hiện tại của bạn sẽ bị xóa. Bạn có muốn tiếp tục?",
    "navigator_error": "Xin lỗi, vẫn bị khóa!",
    "failed_save_rec_file": "Không lưu được tệp đã ghi",
    "failed_get_Rec_file": "Không lấy được tệp đã ghi",
    "select_image": "Chọn ảnh",
    "select_audio": "Chọn âm thanh",
    "rbo_alert": "Lưu ý rằng khi bạn đã gửi, {0} bạn sẽ không thể thay đổi câu trả lời của mình.",
    "video": "Video",
    "audio": "Âm thanh",
    "image": "Hình ảnh",
    "your_score": "Điểm của bạn: {0}",
    "esInfopass": "{0} Câu trả lời đúng để vượt qua",
    "points_earned": "Điểm XP kiếm được: {0} trong số {1}",
    "you_finished_trail": "Bạn đã hoàn thành con đường mòn",
    "summary": "Tóm lược",
    "passed": "THÔNG QUA",
    "failed": "THẤT BẠI",
    "finish": "Hoàn thành",
    "no_data_available": "Không có dữ liệu",
    "rate_required_msg": "Đánh giá và nhận xét là bắt buộc",
    "now_playing": "Đang chơi:",
    "link_sent": "Liên kết đã được gửi",
    "please_check_your_email_box": "Xin vui lòng kiểm tra email của bạn",
    "this_msg_destruct_in": "Thông báo này sẽ kết thúc trong:",
    "back_to_login": "Quay lại đăng nhập",
    "send_reset_link": "Gửi liên kết đặt lại",
    "back": "Trở lại",
    "search_result": "Tìm kêt quả",
    "try_different_or_specific_words": "Thử các cụm từ tìm kiếm khác",
    "dismiss": "Bỏ qua",
    "filter": "Bộ lọc",
    "leave": "Rời khỏi",
    "exit_alert": "Bạn có chắc bạn muốn thoát ?",
    "rating_request": "Yêu cầu xếp hạng",
    "give_rating": "Đưa ra đánh giá",
    "password_has_been_change": "mật khẩu đã được thay đổi",
    "sort_by": "Sắp xếp theo",
    "name_a_z": "Tên AZ",
    "name_z_a": "Tên ZA",
    "rating_received": "Đã nhận được xếp hạng",
    "images": "Hình ảnh",
    "audios": "Âm thanh",
    "videos": "Video",
    "documents": "Các tài liệu",
    "recent_upload": "Tải lên gần đây",
    "most_likes": "Thích nhất",
    "file_size": "Kích thước tập tin",
    "all": "Tất cả",
    "messages": "Tin nhắn",
    "most_liked": "Thích nhất",
    "my_vault": "Hầm của tôi",
    "prize": "Giải thưởng",
    "pts": "pts",
    "complete_your_profile": "Hoàn thành hồ sơ của bạn",
    "picture_uploaded_success": "Hình ảnh của bạn đã được cập nhật thành công",
    "fill_in": "Điền vào",
    "no_ratings_received_yet": "Chưa nhận được xếp hạng nào",
    "i_agree_to_the": "tôi đồng ý với",
    "terms_and_conditions": "Điều khoản và điều kiện",
    "and": "và",
    "privacy_policy": "Chính sách bảo mật",
    "phone_number": "Số điện thoại",
    "you_can_arrange_the_order_by_dragging_each_item": "Bạn có thể sắp xếp thứ tự bằng cách kéo từng mục",
    "experience": "Kinh nghiệm",
    "education": "Giáo dục",
    "less_than_year": "Dưới 1 năm",
    "one_two_years": "1 đến 2 năm",
    "three_five_years": "3 đến 5 năm",
    "six_to_ten_years": "6 đến 10 năm",
    "ele_fifn_years": "11 đến 15 năm",
    "more_twenty_years": "Hơn 20 năm",
    "below_sec": "Dưới trung học",
    "secondary": "Thứ hai",
    "trade_education": "Thương mại \/ Kỹ thuật \/ Dạy nghề",
    "associate": "Cao đẳng \/ Cao đẳng",
    "bachelor": "Cử nhân",
    "master_education": "Thạc sĩ \/ Chuyên nghiệp",
    "doctoral": "Tiến sĩ",
    "male": "Nam giới",
    "female": "Giống cái",
    "non_binary": "Phi nhị phân",
    "please_select_your_country": "vui lòng chọn đất nước của bạn",
    "account_info": "Thông tin tài khoản",
    "other_info": "Thông tin khác",
    "password_confirmation": "xác nhận mật khẩu",
    "search_chats": "Tìm kiếm các cuộc trò chuyện",
    "type_a_message": "Gõ một tin nhắn",
    "start_chat": "Bắt đầu trò chuyện",
    "select_a_contact_and_start_chat": "Chọn liên hệ và bắt đầu trò chuyện",
    "ive_won": "tôi đã thắng",
    "ive_lost": "Tôi đã thua",
    "waiting_opponent": "Chờ đối thủ",
    "player_ranking": "Xếp hạng người chơi",
    "team_ranking": "Xếp hạng đội",
    "latest_profile_image": "Hình ảnh hồ sơ mới nhất",
    "latest_images_uploaded": "Hình ảnh mới nhất được tải lên",
    "status": "Trạng thái",
    "coach": "Huấn luyện viên",
    "current_path": "Muộn nhất",
    "learn": "Học hỏi",
    "battle": "Trận chiến",
    "exam": "Thi",
    "survey": "Khảo sát",
    "locked": "Đã khóa",
    "started": "Đã bắt đầu",
    "your_path": "Con đường của bạn",
    "extra_path": "Thêm",
    "type": "Kiểu",
    "time": "Thời gian",
    "level": "Cấp độ",
    "due": "Đến hạn",
    "pending": "Đang chờ xử lý",
    "days": "ngày",
    "seconds": "giây",
    "minutes": "phút",
    "hours": "giờ",
    "open": "Mở",
    "view_details": "Xem chi tiết",
    "xp": "xp",
    "pending_battles": "Trận đánh đang chờ xử lý",
    "step": "bươc",
    "details": "Chi tiết",
    "custom": "Tập quán",
    "profile_complete": "{0} trong tổng số hồ sơ đã hoàn tất!",
    "achievements": "Thành tựu",
    "battles_played": "{0} trận chiến đã chơi",
    "finished_trail_on": "Đã hoàn thành đường mòn trên {0}",
    "ratings": "Xếp hạng",
    "player_activity": "Hoạt động của người chơi",
    "max": "Tối đa {0}",
    "answer": "{\"one\":\"{0} answer\",\"other\":\"{0} answers\"}",
    "pipe_sym": "|",
    "w": "W",
    "d": "D",
    "l": "L",
    "overview": "Tổng quat",
    "my_team": "Đội của tôi",
    "save": "Tiết kiệm",
    "play_again": "Chơi lại",
    "please_choose_your_opponent": "Hãy chọn đối thủ của bạn",
    "edit": "Biên tập",
    "required": "Cần thiết",
    "optional": "Không bắt buộc",
    "choose": "Chọn",
    "member": "{\"one\":\"{0} member\",\"other\":\"{0} members\"}",
    "hrs": "giờ",
    "min": "min",
    "sec": "giây",
    "from_battles_played": "Từ {0} trận chiến đã chơi",
    "choose_your_opponent": "Chọn đối thủ của bạn",
    "completed_survey_on": "Đã hoàn thành khảo sát vào {0}",
    "passed_exam_on": "Đã vượt qua bài kiểm tra vào {0}",
    "failed_exam_on": "Không thực hiện được bài kiểm tra vào {0}",
    "from_rater": "Từ {0}",
    "thank_you_subtitle": "Tìm hiểu thêm về riaplay trong",
    "download_title": "Tải xuống",
    "error_page_msg": "Karel đang làm việc với nó. Xin lỗi vì sự bất tiện gây ra!",
    "exams": "Kỳ thi",
    "assess_result_title_me": "Dữ liệu kết quả thuộc về tôi",
    "assess_result_title_team": "Dữ liệu kết quả thuộc về nhóm của tôi",
    "assess_result_title_all": "Dữ liệu kết quả thuộc về công ty của tôi",
    "personal_info_updated_success": "Thông tin cá nhân được cập nhật thành công",
    "language_updated_success": "Đã cập nhật ngôn ngữ thành công",
    "fields_updated_success": "Các trường được cập nhật thành công",
    "profile_updated_success": "Đã cập nhật ảnh hồ sơ thành công",
    "cover_updated_success": "Đã cập nhật ảnh bìa thành công",
    "supported_formats": "Các định dạng được hỗ trợ",
    "seconds_played": "{0} giây đã chơi",
    "minutes_played": "{0} phút",
    "hours_played": "{0} giờ đã chơi",
    "days_played": "{0} ngày đã chơi",
    "result_downloaded_successfully": "Tệp đã được tải xuống và lưu vào thiết bị của bạn thành công",
    "download_ask_for_permission": "Ứng dụng không có quyền lưu tệp trên thiết bị, vui lòng cho phép nó từ cài đặt"
}